abxr/api_service.py
abxr/app_bundles.py
abxr/apps.py
abxr/audit_logs.py
abxr/cli.py
abxr/constants.py
abxr/devices.py
abxr/files.py
abxr/formats.py
abxr/groups.py
abxr/multipart.py
abxr/org.py
abxr/output.py
abxr/system_apps.py
abxr/tags.py
abxr/users.py
abxr/version.py
abxr/videos.py
abxrcli-0.15.2.dist-info/licenses/LICENSE
abxrcli-0.15.2.dist-info/METADATA
abxrcli-0.15.2.dist-info/WHEEL
abxrcli-0.15.2.dist-info/entry_points.txt
abxrcli-0.15.2.dist-info/top_level.txt
abxrcli-0.15.2.dist-info/RECORD
