Metadata-Version: 2.4
Name: abxrcli
Version: 0.15.2
Summary: ArborXR CLI
Author-email: Peter Peterson <peter@arborxr.com>
License-File: LICENSE
Requires-Dist: setuptools
Requires-Dist: requests
Requires-Dist: tqdm
Requires-Dist: pyyaml
Dynamic: license-file
